aimlpkit/__init__.py
aimlpkit/main.py
aimlpkit-0.3.0.dist-info/METADATA
aimlpkit-0.3.0.dist-info/WHEEL
aimlpkit-0.3.0.dist-info/top_level.txt
aimlpkit-0.3.0.dist-info/RECORD
