Metadata-Version: 2.4
Name: aimlpkit
Version: 0.3.0
Requires-Python: >=3.10
Requires-Dist: setuptools>=80.9.0
Requires-Dist: twine>=6.2.0
